LICENSE
MANIFEST.in
NOTICE
README.rst
setup.py
./BoxKit.egg-info/PKG-INFO
./BoxKit.egg-info/SOURCES.txt
./BoxKit.egg-info/dependency_links.txt
./BoxKit.egg-info/requires.txt
./BoxKit.egg-info/top_level.txt
./boxkit/__init__.py
./boxkit/__meta__.py
./boxkit/options.py
./boxkit/api/__init__.py
./boxkit/api/_create.py
./boxkit/api/_mean.py
./boxkit/api/_mergeblocks.py
./boxkit/api/_read.py
./boxkit/api/_regionprops.py
./boxkit/api/_resfilter.py
./boxkit/cbox/__init__.py
./boxkit/cbox/lib/__init__.py
./boxkit/cbox/lib/boost.py
./boxkit/cbox/lib/extern.py
./boxkit/cbox/lib/library.so
./boxkit/library/__init__.py
./boxkit/library/_action.py
./boxkit/library/_block.py
./boxkit/library/_data.py
./boxkit/library/_dataset.py
./boxkit/library/_execute.py
./boxkit/library/_monitor.py
./boxkit/library/_region.py
./boxkit/library/_resources.py
./boxkit/library/_server.py
./boxkit/library/_slice.py
./boxkit/library/_timer.py
./boxkit/resources/__init__.py
./boxkit/resources/read/__init__.py
./boxkit/resources/read/_flash.py
./boxkit/resources/read/_sample.py
bin/boost.py
bin/cbox.py
bin/cmd.py
boxkit/cbox/__init__.py
boxkit/cbox/__pycache__/__init__.cpython-38.pyc
boxkit/cbox/include/cbox/library.h
boxkit/cbox/include/cbox/pytypes.hpp
boxkit/cbox/lib/__init__.py
boxkit/cbox/lib/boost.py
boxkit/cbox/lib/extern.py
boxkit/cbox/lib/library.so
boxkit/cbox/lib/__pycache__/__init__.cpython-38.pyc
boxkit/cbox/lib/__pycache__/boost.cpython-38.pyc
boxkit/cbox/lib/__pycache__/extern.cpython-38.pyc
boxkit/cbox/source/Make.inc
boxkit/cbox/source/Makefile
boxkit/cbox/source/action.cpp
boxkit/cbox/source/block.cpp
boxkit/cbox/source/data.cpp
boxkit/cbox/source/execute.cpp
boxkit/cbox/source/library.cpp
boxkit/cbox/source/monitor.cpp
boxkit/cbox/source/region.cpp
boxkit/depends/indicators/LICENSE
boxkit/depends/indicators/block_progress_bar.hpp
boxkit/depends/indicators/color.hpp
boxkit/depends/indicators/cursor_control.hpp
boxkit/depends/indicators/cursor_movement.hpp
boxkit/depends/indicators/display_width.hpp
boxkit/depends/indicators/dynamic_progress.hpp
boxkit/depends/indicators/font_style.hpp
