Metadata-Version: 2.1
Name: BoxKit
Version: 2023.9.1
Summary: BoxKit utility
Author: Akash Dhruv
License: Apache Software License
Classifier: Programming Language :: Python :: 3.8
Classifier: License :: OSI Approved :: Apache Software License
License-File: LICENSE
License-File: NOTICE
Requires-Dist: numpy
Requires-Dist: h5py
Requires-Dist: h5pickle
Requires-Dist: pymorton
Requires-Dist: joblib
Requires-Dist: tqdm
Requires-Dist: toml
Requires-Dist: psutil
Requires-Dist: progress
